nodeimage/__init__.py
nodeimage/__main__.py
nodeimage/__version__.py
nodeimage/_cli.py
nodeimage/_client.py
nodeimage/_utils.py
nodeimage/py.typed
nodeimage-0.0.2.dist-info/licenses/LICENSE
nodeimage-0.0.2.dist-info/METADATA
nodeimage-0.0.2.dist-info/WHEEL
nodeimage-0.0.2.dist-info/entry_points.txt
nodeimage-0.0.2.dist-info/top_level.txt
nodeimage-0.0.2.dist-info/RECORD
