Metadata-Version: 2.4
Name: nodeimage
Version: 0.0.2
Summary: NodeImage Python CLI Client
Author-email: 0x0208v0 <0x0208v0@github.com>
License-Expression: MIT
Project-URL: Homepage, https://github.com/0x0208v0/nodeimage
Project-URL: Source, https://github.com/0x0208v0/nodeimage
Classifier: Development Status :: 4 - Beta
Classifier: Environment :: Console
Classifier: Intended Audience :: Developers
Classifier: Intended Audience :: End Users/Desktop
Classifier: Operating System :: OS Independent
Classifier: Programming Language :: Python :: 3
Classifier: Programming Language :: Python :: 3.9
Classifier: Programming Language :: Python :: 3.10
Classifier: Programming Language :: Python :: 3.11
Classifier: Programming Language :: Python :: 3.12
Classifier: Topic :: Internet :: WWW/HTTP
Classifier: Topic :: Multimedia :: Graphics
Classifier: Topic :: Software Development :: Libraries :: Python Modules
Classifier: Topic :: System :: Archiving
Classifier: Topic :: Utilities
Requires-Python: >=3.9
License-File: LICENSE
Requires-Dist: click
Requires-Dist: httpx[socks]
Requires-Dist: typing_extensions
Requires-Dist: python-dotenv
Requires-Dist: openpyxl
Dynamic: license-file
